pyudbf/UDBFBytesReader.py
pyudbf/UDBFData.py
pyudbf/UDBFFileReader.py
pyudbf/UDBFParser.py
pyudbf/__init__.py
pyudbf-0.3.0.dist-info/LICENSE
pyudbf-0.3.0.dist-info/METADATA
pyudbf-0.3.0.dist-info/WHEEL
pyudbf-0.3.0.dist-info/top_level.txt
pyudbf-0.3.0.dist-info/RECORD
