Metadata-Version: 2.1
Name: pyudbf
Version: 0.3.0
Summary: A python implementation of the UDBF (Universal Data bin File) format.
Author: Gerrit Spengler
Project-URL: Homepage, https://github.com/dvnll/pyudbf
Project-URL: Issues, https://github.com/dvnll/pyudbf/issues
Classifier: Programming Language :: Python :: 3
Classifier: License :: OSI Approved :: MIT License
Classifier: Operating System :: OS Independent
Requires-Python: >=3.8
License-File: LICENSE
Requires-Dist: numpy>=2.0.0
Requires-Dist: datetime
